envtwin/__init__.py
envtwin/__main__.py
envtwin/dockerize.py
envtwin/setupscript.py
envtwin/share.py
envtwin/snapshot.py
envtwin/utils.py
envtwin-1.1.3.dist-info/licenses/LICENSE
envtwin-1.1.3.dist-info/METADATA
envtwin-1.1.3.dist-info/WHEEL
envtwin-1.1.3.dist-info/top_level.txt
envtwin-1.1.3.dist-info/RECORD
