Metadata-Version: 2.4
Name: envtwin
Version: 1.1.3
Summary: Instant Environment Recreator: snapshot and share your dev environment.
Author: Syntax-XXX
License: MIT
Requires-Python: >=3.6
License-File: LICENSE
Dynamic: author
Dynamic: license-file
Dynamic: requires-python
